euroleague/__init__.py
euroleague/_version.py
euroleague/api/__init__.py
euroleague/api/base.py
euroleague/api/live/__init__.py
euroleague/api/live/play_by_play.py
euroleague/api/live/shots.py
euroleague/api/v1/__init__.py
euroleague/api/v1/games.py
euroleague/api/v1/players.py
euroleague/api/v1/results.py
euroleague/api/v1/schedules.py
euroleague/api/v1/standings.py
euroleague/api/v1/teams.py
euroleague/api/v2/__init__.py
euroleague/api/v2/clubs.py
euroleague/api/v2/competitions.py
euroleague/api/v2/games.py
euroleague/api/v2/groups.py
euroleague/api/v2/people.py
euroleague/api/v2/phases.py
euroleague/api/v2/records.py
euroleague/api/v2/referees.py
euroleague/api/v2/rounds.py
euroleague/api/v2/season_clubs.py
euroleague/api/v2/season_people.py
euroleague/api/v2/seasons.py
euroleague/api/v2/standings.py
euroleague/api/v2/stats.py
euroleague/api/v3/__init__.py
euroleague/api/v3/clubs.py
euroleague/api/v3/coaches.py
euroleague/api/v3/games.py
euroleague/api/v3/player_stats.py
euroleague/api/v3/standings.py
euroleague/api/v3/stats.py
euroleague/api/v3/team_stats.py
euroleague/client.py
euroleague/exceptions.py
euroleague/http.py
euroleague/models/__init__.py
euroleague/models/base.py
euroleague/models/common.py
euroleague/models/live/__init__.py
euroleague/models/live/play_by_play.py
euroleague/models/live/shots.py
euroleague/models/v1/__init__.py
euroleague/models/v2/__init__.py
euroleague/models/v3/__init__.py
euroleague/utils/__init__.py
euroleague/utils/constants.py
py_euroleague-0.2.1.dist-info/METADATA
py_euroleague-0.2.1.dist-info/WHEEL
py_euroleague-0.2.1.dist-info/licenses/LICENSE
py_euroleague-0.2.1.dist-info/RECORD
