Metadata-Version: 2.4
Name: py-euroleague
Version: 0.2.1
Summary: Python wrapper for the Euroleague Basketball API
License: MIT
License-File: LICENSE
Keywords: euroleague,basketball,api,sports,eurocup,eurobasket
Author: sfendourakis
Author-email: sfendourakispan@gmail.com
Requires-Python: >=3.10
Classifier: Development Status :: 4 - Beta
Classifier: Intended Audience :: Developers
Classifier: License :: OSI Approved :: MIT License
Classifier: Operating System :: OS Independent
Classifier: Programming Language :: Python :: 3
Classifier: Programming Language :: Python :: 3.10
Classifier: Programming Language :: Python :: 3.11
Classifier: Programming Language :: Python :: 3.12
Classifier: Programming Language :: Python :: 3.13
Classifier: Programming Language :: Python :: 3.14
Classifier: Topic :: Software Development :: Libraries :: Python Modules
Classifier: Typing :: Typed
Requires-Dist: httpx (>=0.27.0)
Requires-Dist: pydantic (>=2.0.0)
Project-URL: Changelog, https://github.com/sfendourakis/py-euroleague/blob/main/CHANGELOG.md
Project-URL: Homepage, https://github.com/sfendourakis/py-euroleague
Project-URL: Issues, https://github.com/sfendourakis/py-euroleague/issues
Project-URL: Repository, https://github.com/sfendourakis/py-euroleague
